sudo_ai/__init__.py
sudo_ai/_version.py
sudo_ai/basesdk.py
sudo_ai/httpclient.py
sudo_ai/py.typed
sudo_ai/responses.py
sudo_ai/router.py
sudo_ai/sdk.py
sudo_ai/sdkconfiguration.py
sudo_ai/system.py
sudo_ai/_hooks/__init__.py
sudo_ai/_hooks/registration.py
sudo_ai/_hooks/sdkhooks.py
sudo_ai/_hooks/types.py
sudo_ai/errors/__init__.py
sudo_ai/errors/errorresponse.py
sudo_ai/errors/no_response_error.py
sudo_ai/errors/responsevalidationerror.py
sudo_ai/errors/sudodefaulterror.py
sudo_ai/errors/sudoerror.py
sudo_ai/models/__init__.py
sudo_ai/models/chatcompletion.py
sudo_ai/models/chatcompletionchunk.py
sudo_ai/models/chatcompletionchunkchoice.py
sudo_ai/models/chatcompletiondelta.py
sudo_ai/models/chatcompletionlist.py
sudo_ai/models/chatcompletionrequestjson.py
sudo_ai/models/chatcompletionrequeststream.py
sudo_ai/models/chatdeletionconfirmation.py
sudo_ai/models/chatmessage.py
sudo_ai/models/chatmessagelist.py
sudo_ai/models/choice.py
sudo_ai/models/contentpart_union.py
sudo_ai/models/deletechatcompletionop.py
sudo_ai/models/errordetail.py
sudo_ai/models/function.py
sudo_ai/models/getchatcompletionmessagesop.py
sudo_ai/models/getchatcompletionop.py
sudo_ai/models/imagedata.py
sudo_ai/models/imagegeneration.py
sudo_ai/models/imagegenerationrequest.py
sudo_ai/models/imageinputtokens.py
sudo_ai/models/imageusage.py
sudo_ai/models/inputitem_union.py
sudo_ai/models/item_union.py
sudo_ai/models/listchatcompletionsop.py
sudo_ai/models/messagecontent.py
sudo_ai/models/messageresponse.py
sudo_ai/models/outputmessage.py
sudo_ai/models/response.py
sudo_ai/models/responseevent.py
sudo_ai/models/responsesrequest.py
sudo_ai/models/responsesrequeststream.py
sudo_ai/models/returnedchatmessages.py
sudo_ai/models/security.py
sudo_ai/models/supportedmodel.py
sudo_ai/models/supportedmodelslist.py
sudo_ai/models/tool.py
sudo_ai/models/toolcall.py
sudo_ai/models/toolcallfunction.py
sudo_ai/models/toolcalloutput.py
sudo_ai/models/updatechatcompletionop.py
sudo_ai/models/usage.py
sudo_ai-0.2.2.dist-info/METADATA
sudo_ai-0.2.2.dist-info/WHEEL
sudo_ai-0.2.2.dist-info/top_level.txt
sudo_ai-0.2.2.dist-info/RECORD
