Metadata-Version: 2.4
Name: sudo-ai
Version: 0.2.2
Summary: The official Python Client SDK for the Sudo API. Generated by Speakeasy
Author: Speakeasy, Sudo
Requires-Python: >=3.9.2
Requires-Dist: httpcore>=1.0.9
Requires-Dist: httpx>=0.28.1
Requires-Dist: pydantic>=2.11.2
